{
  "commission_name": "УИК №1568",
  "ballot_name": "Выборы депутатов Законодательного Собрания Санкт-Петербурга седьмого созыва",
  "name": "Результаты выборов по одномандатному (многомандатному) округу",
  "protocol_scope": {
    "type": "uik",
    "id": 1568
  },
  "electoral_district": {
    "type": "city",
    "id": 23
  },
  "data_id": 27820001915220,
  "ballot_data_id": 4784022367909,
  "has_koib": false,
  "generated_date": 1632124597000,
  "official_result": {
    "winner": {
      "id": 232,
      "position": 1,
      "percentage": 36.098310291858674,
      "valid_percentage": 37.124802527646125,
      "registered_percentage": 16.596045197740114
    },
    "turnout": {
      "count": 659,
      "percentage": 46.53954802259887,
      "walk_by_count": 646,
      "walk_by_percentage": 45.62146892655367,
      "on_home_count": 13,
      "on_home_percentage": 0.9180790960451978,
      "ahead_of_time_count": 0,
      "ahead_of_time_percentage": 0,
      "valid_count": 633,
      "valid_percentage": 44.70338983050847,
      "invalid_count": 18,
      "invalid_percentage": 1.2711864406779663,
      "taken_home_count": 8,
      "taken_home_percentage": 0.5649717514124294,
      "lost_count": 0,
      "lost_percentage": 0
    },
    "votes_stats": {
      "winning_count": 235,
      "winning_percentage": 36.098310291858674,
      "effective_count": 633,
      "losing_count": 398,
      "losing_percentage": 61.136712749615974,
      "other_count": 18,
      "other_percentage": 2.7649769585253456,
      "by_place": {
        "#1": {
          "count": 235,
          "percentage": 36.098310291858674
        },
        "#2": {
          "count": 102,
          "percentage": 15.668202764976957,
          "supported_by_smart_vote": true
        },
        "#3": {
          "count": 96,
          "percentage": 14.746543778801843
        },
        "#4": {
          "count": 64,
          "percentage": 9.831029185867896
        },
        "#5": {
          "count": 50,
          "percentage": 7.680491551459294
        },
        "#6": {
          "count": 44,
          "percentage": 6.7588325652841785
        },
        "#7": {
          "count": 42,
          "percentage": 6.451612903225806
        }
      }
    }
  },
  "turnout_protocols": {
    "17.09.2021": {
      "15.00": {
        "count": 153,
        "count_delta": 153,
        "count_delta_per_hour": 21.857142857142858,
        "count_delta_per_minute": 0.36428571428571427,
        "percentage": 10.87,
        "percentage_delta": 10.87,
        "percentage_delta_per_hour": 1.5528571428571427,
        "percentage_delta_per_minute": 0.02588095238095238,
        "registered_count": 1408,
        "registered_count_delta": 1408,
        "registered_count_delta_per_hour": 201.14285714285714,
        "registered_count_delta_per_minute": 3.3523809523809525
      },
      "20.00": {
        "count": 244,
        "count_delta": 91,
        "count_delta_per_hour": 18.2,
        "count_delta_per_minute": 0.30333333333333334,
        "percentage": 17.33,
        "percentage_delta": 6.459999999999999,
        "percentage_delta_per_hour": 1.2919999999999998,
        "percentage_delta_per_minute": 0.02153333333333333,
        "registered_count": 1408,
        "registered_count_delta": 0,
        "registered_count_delta_per_hour": 0,
        "registered_count_delta_per_minute": 0
      }
    },
    "18.09.2021": {
      "15.00": {
        "count": 316,
        "count_delta": 72,
        "count_delta_per_hour": 10.285714285714286,
        "count_delta_per_minute": 0.17142857142857143,
        "percentage": 22.44,
        "percentage_delta": 5.110000000000003,
        "percentage_delta_per_hour": 0.7300000000000004,
        "percentage_delta_per_minute": 0.012166666666666675,
        "registered_count": 1408,
        "registered_count_delta": 0,
        "registered_count_delta_per_hour": 0,
        "registered_count_delta_per_minute": 0
      },
      "20.00": {
        "count": 351,
        "count_delta": 35,
        "count_delta_per_hour": 7,
        "count_delta_per_minute": 0.11666666666666667,
        "percentage": 24.93,
        "percentage_delta": 2.4899999999999984,
        "percentage_delta_per_hour": 0.49799999999999967,
        "percentage_delta_per_minute": 0.008299999999999995,
        "registered_count": 1408,
        "registered_count_delta": 0,
        "registered_count_delta_per_hour": 0,
        "registered_count_delta_per_minute": 0
      }
    },
    "19.09.2021": {
      "10.00": {
        "count": 365,
        "count_delta": 14,
        "count_delta_per_hour": 7,
        "count_delta_per_minute": 0.11666666666666667,
        "percentage": 25.78,
        "percentage_delta": 0.8500000000000014,
        "percentage_delta_per_hour": 0.4250000000000007,
        "percentage_delta_per_minute": 0.007083333333333345
      },
      "12.00": {
        "count": 392,
        "count_delta": 27,
        "count_delta_per_hour": 13.5,
        "count_delta_per_minute": 0.225,
        "percentage": 27.7,
        "percentage_delta": 1.9199999999999982,
        "percentage_delta_per_hour": 0.9599999999999991,
        "percentage_delta_per_minute": 0.015999999999999983
      },
      "15.00": {
        "count": 476,
        "count_delta": 84,
        "count_delta_per_hour": 28,
        "count_delta_per_minute": 0.4666666666666667,
        "percentage": 33.64,
        "percentage_delta": 5.940000000000001,
        "percentage_delta_per_hour": 1.9800000000000004,
        "percentage_delta_per_minute": 0.03300000000000001
      },
      "18.00": {
        "count": 552,
        "count_delta": 76,
        "count_delta_per_hour": 25.333333333333332,
        "count_delta_per_minute": 0.4222222222222222,
        "percentage": 38.97,
        "percentage_delta": 5.329999999999998,
        "percentage_delta_per_hour": 1.7766666666666662,
        "percentage_delta_per_minute": 0.029611111111111102
      },
      "20.00": {
        "count": 659,
        "count_delta": 107,
        "count_delta_per_hour": 53.5,
        "count_delta_per_minute": 0.8916666666666667,
        "percentage": 46.53954802259887,
        "percentage_delta": 7.569548022598873,
        "percentage_delta_per_hour": 3.7847740112994366,
        "percentage_delta_per_minute": 0.06307956685499061,
        "registered_count": 1416,
        "registered_count_delta": 8,
        "registered_count_delta_per_hour": 0.6666666666666666,
        "registered_count_delta_per_minute": 0.011111111111111112
      }
    }
  },
  "metadata": {
    "analysis": {
      "protocol_count": 1,
      "exceeded_papers_count": 0,
      "exceeded_papers_steal_winning": 0,
      "checksum_valid": 1,
      "stuffed_protocol_for_236": 1,
      "stuffed_votes_for_236": 35.68898488120951
    },
    "voters": {
      "initially_registered_count": 1408,
      "registered_count": 1416,
      "walk_by_count": 646,
      "on_home_count": 13,
      "ahead_of_time_count": 0,
      "exceptional_count": 0,
      "added_count": 8
    },
    "papers": {
      "received_count": 1100,
      "destroyed_count": 441,
      "stationary_box_count": 638,
      "portable_box_count": 13,
      "valid_count": 633,
      "invalid_count": 18,
      "lost_count": 0,
      "ignored_count": 0,
      "taken_home_count": 8
    }
  },
  "entries": [
    {
      "name": "Авдеев Юрий Васильевич",
      "position": 1,
      "candidate_id": 232,
      "supported_by_party_id": 5,
      "official_result": {
        "votes_count": 235,
        "place": 1,
        "percentage": 36.098310291858674,
        "valid_percentage": 37.124802527646125,
        "registered_percentage": 16.596045197740114,
        "display_percentage": 36.1,
        "winner": true
      },
      "result_without_other_entry": {
        "61": {
          "percentage": 42.80510018214937,
          "valid_percentage": 44.25612052730697
        },
        "64": {
          "percentage": 40.03407155025553,
          "valid_percentage": 41.30052724077329
        },
        "233": {
          "percentage": 38.71499176276771,
          "valid_percentage": 39.898132427843805
        },
        "234": {
          "percentage": 38.587848932676515,
          "valid_percentage": 39.76311336717428
        },
        "235": {
          "percentage": 39.10149750415973,
          "valid_percentage": 40.308747855917666
        },
        "236": {
          "percentage": 42.34234234234234,
          "valid_percentage": 43.76163873370577
        }
      }
    },
    {
      "name": "Бакулин Владислав Юрьевич",
      "position": 2,
      "candidate_id": 61,
      "supported_by_party_id": 8,
      "supported_by_smart_vote": true,
      "official_result": {
        "votes_count": 102,
        "place": 2,
        "percentage": 15.668202764976957,
        "valid_percentage": 16.113744075829384,
        "registered_percentage": 7.203389830508475,
        "display_percentage": 15.67,
        "winner": false,
        "lacking_votes_count": 133
      },
      "result_without_other_entry": {
        "64": {
          "percentage": 17.37649063032368,
          "valid_percentage": 17.926186291739896
        },
        "232": {
          "percentage": 24.519230769230766,
          "valid_percentage": 25.628140703517587
        },
        "233": {
          "percentage": 16.80395387149918,
          "valid_percentage": 17.31748726655348
        },
        "234": {
          "percentage": 16.748768472906402,
          "valid_percentage": 17.258883248730964
        },
        "235": {
          "percentage": 16.97171381031614,
          "valid_percentage": 17.495711835334475
        },
        "236": {
          "percentage": 18.37837837837838,
          "valid_percentage": 18.994413407821227
        }
      }
    },
    {
      "name": "Сазонцев Евгений Павлович",
      "position": 7,
      "candidate_id": 236,
      "supported_by_party_id": 1,
      "official_result": {
        "votes_count": 96,
        "place": 3,
        "percentage": 14.746543778801843,
        "valid_percentage": 15.165876777251185,
        "registered_percentage": 6.779661016949152,
        "display_percentage": 14.75,
        "winner": false,
        "lacking_votes_count": 139
      },
      "result_without_other_entry": {
        "61": {
          "percentage": 17.48633879781421,
          "valid_percentage": 18.07909604519774
        },
        "64": {
          "percentage": 16.35434412265758,
          "valid_percentage": 16.87170474516696
        },
        "232": {
          "percentage": 23.076923076923077,
          "valid_percentage": 24.120603015075375
        },
        "233": {
          "percentage": 15.815485996705107,
          "valid_percentage": 16.298811544991512
        },
        "234": {
          "percentage": 15.763546798029557,
          "valid_percentage": 16.243654822335024
        },
        "235": {
          "percentage": 15.973377703826955,
          "valid_percentage": 16.466552315608922
        }
      }
    },
    {
      "name": "Горячева Ксения Александровна",
      "position": 4,
      "candidate_id": 64,
      "supported_by_party_id": 4,
      "official_result": {
        "votes_count": 64,
        "place": 4,
        "percentage": 9.831029185867896,
        "valid_percentage": 10.110584518167457,
        "registered_percentage": 4.519774011299435,
        "display_percentage": 9.83,
        "winner": false,
        "lacking_votes_count": 171
      },
      "result_without_other_entry": {
        "61": {
          "percentage": 11.657559198542804,
          "valid_percentage": 12.052730696798493
        },
        "232": {
          "percentage": 15.384615384615385,
          "valid_percentage": 16.08040201005025
        },
        "233": {
          "percentage": 10.543657331136739,
          "valid_percentage": 10.865874363327674
        },
        "234": {
          "percentage": 10.50903119868637,
          "valid_percentage": 10.829103214890017
        },
        "235": {
          "percentage": 10.64891846921797,
          "valid_percentage": 10.977701543739279
        },
        "236": {
          "percentage": 11.531531531531531,
          "valid_percentage": 11.91806331471136
        }
      }
    },
    {
      "name": "Романовский Денис Николаевич",
      "position": 6,
      "candidate_id": 235,
      "supported_by_party_id": 6,
      "official_result": {
        "votes_count": 50,
        "place": 5,
        "percentage": 7.680491551459294,
        "valid_percentage": 7.898894154818326,
        "registered_percentage": 3.531073446327684,
        "display_percentage": 7.68,
        "winner": false,
        "lacking_votes_count": 185
      },
      "result_without_other_entry": {
        "61": {
          "percentage": 9.107468123861565,
          "valid_percentage": 9.416195856873824
        },
        "64": {
          "percentage": 8.517887563884157,
          "valid_percentage": 8.787346221441124
        },
        "232": {
          "percentage": 12.01923076923077,
          "valid_percentage": 12.562814070351758
        },
        "233": {
          "percentage": 8.237232289950576,
          "valid_percentage": 8.488964346349745
        },
        "234": {
          "percentage": 8.210180623973727,
          "valid_percentage": 8.460236886632826
        },
        "236": {
          "percentage": 9.00900900900901,
          "valid_percentage": 9.31098696461825
        }
      }
    },
    {
      "name": "Горохов Дмитрий Андреевич",
      "position": 3,
      "candidate_id": 233,
      "supported_by_party_id": 7,
      "official_result": {
        "votes_count": 44,
        "place": 6,
        "percentage": 6.7588325652841785,
        "valid_percentage": 6.9510268562401265,
        "registered_percentage": 3.1073446327683616,
        "display_percentage": 6.76,
        "winner": false,
        "lacking_votes_count": 191
      },
      "result_without_other_entry": {
        "61": {
          "percentage": 8.014571948998178,
          "valid_percentage": 8.286252354048965
        },
        "64": {
          "percentage": 7.495741056218058,
          "valid_percentage": 7.732864674868189
        },
        "232": {
          "percentage": 10.576923076923077,
          "valid_percentage": 11.055276381909549
        },
        "234": {
          "percentage": 7.224958949096879,
          "valid_percentage": 7.4450084602368864
        },
        "235": {
          "percentage": 7.321131447587355,
          "valid_percentage": 7.547169811320755
        },
        "236": {
          "percentage": 7.927927927927928,
          "valid_percentage": 8.193668528864059
        }
      }
    },
    {
      "name": "Котельников Сергей Александрович",
      "position": 5,
      "candidate_id": 234,
      "supported_by_party_id": 3,
      "official_result": {
        "votes_count": 42,
        "place": 7,
        "percentage": 6.451612903225806,
        "valid_percentage": 6.6350710900473935,
        "registered_percentage": 2.9661016949152543,
        "display_percentage": 6.45,
        "winner": false,
        "lacking_votes_count": 193
      },
      "result_without_other_entry": {
        "61": {
          "percentage": 7.650273224043716,
          "valid_percentage": 7.909604519774012
        },
        "64": {
          "percentage": 7.155025553662692,
          "valid_percentage": 7.381370826010544
        },
        "232": {
          "percentage": 10.096153846153847,
          "valid_percentage": 10.552763819095476
        },
        "233": {
          "percentage": 6.919275123558484,
          "valid_percentage": 7.130730050933787
        },
        "235": {
          "percentage": 6.988352745424292,
          "valid_percentage": 7.204116638078903
        },
        "236": {
          "percentage": 7.567567567567568,
          "valid_percentage": 7.82122905027933
        }
      }
    }
  ],
  "related_to": {
    "venue": {
      "type": "uik",
      "id": 1568
    },
    "uik": 1568,
    "district": "Невский район",
    "tik": 24,
    "gik": "СПбИК"
  }
}