{
  "id": 24034,
  "data_id": 4784030198107,
  "name": {
    "last": "Вохминцева",
    "first": "Галина",
    "middle": "Николаевна"
  },
  "birthdate": {
    "day": 23,
    "month": 3,
    "year": 1961
  },
  "district": "Центральный район",
  "age": 60,
  "gender": "female",
  "father_name_guess": {
    "last": "Вохминцев",
    "first": "Николай"
  },
  "role_id": 4,
  "assigned_by_id": 28,
  "related_to": {
    "venue": {
      "type": "uik",
      "id": 2264
    },
    "uik": 2264,
    "district": "Центральный район",
    "tik": 64,
    "gik": "СПбИК"
  }
}