{
  "id": 459,
  "data_id": 4784002403223,
  "name": {
    "last": "Каграманян",
    "first": "Игорь",
    "middle": "Борисович"
  },
  "birthdate": {
    "day": 1,
    "month": 1,
    "year": 1993
  },
  "district": "Василеостровский район",
  "age": 28,
  "gender": "male",
  "father_name_guess": {
    "last": "Каграманян",
    "first": "Борис"
  },
  "role_id": 4,
  "assigned_by_id": 13,
  "related_to": {
    "venue": {
      "type": "tik",
      "id": 2
    },
    "tik": 2,
    "district": "Василеостровский район",
    "gik": "СПбИК"
  }
}