{
  "id": 5398,
  "data_id": 4784018248079,
  "name": {
    "last": "Котельников",
    "first": "Сергей",
    "middle": "Александрович"
  },
  "birthdate": {
    "day": 14,
    "month": 12,
    "year": 1974
  },
  "district": "Выборгский район",
  "age": 46,
  "gender": "male",
  "father_name_guess": {
    "last": "Котельников",
    "first": "Александр"
  },
  "role_id": 2,
  "assigned_by_id": 2,
  "related_to": {
    "venue": {
      "type": "uik",
      "id": 299
    },
    "uik": 299,
    "district": "Выборгский район",
    "tik": 14,
    "gik": "СПбИК"
  },
  "relative_candidates": {
    "summary": {
      "total_guess_count": 1,
      "strong_guess_count": 1,
      "strong_guesses": {
        "same_commission": 1
      },
      "siblings_in_commission": {
        "count": 1,
        "ids": 5397
      }
    },
    "siblings": {
      "5397": {
        "strong_evidence": "same_commission",
        "age_difference": -1,
        "name": {
          "last": "Котельникова",
          "first": "Яна",
          "middle": "Александровна"
        },
        "distance": 0,
        "district": "Выборгский район",
        "related_to": {
          "venue": {
            "type": "uik",
            "id": 299
          },
          "uik": 299,
          "district": "Выборгский район",
          "tik": 14,
          "gik": "СПбИК"
        }
      }
    }
  }
}